datanest/__init__.py
datanest-1.0.0.dist-info/LICENSE
datanest-1.0.0.dist-info/WHEEL
datanest-1.0.0.dist-info/METADATA
datanest-1.0.0.dist-info/RECORD
