Metadata-Version: 2.1
Name: datanest
Version: 1.0.0
Summary: A simple, intuitive, pandas-based database.
Author-email: Praneeth Namburi <praneeth.namburi@gmail.com>
Requires-Python: >=3.7
Classifier: Development Status :: 5 - Production/Stable
Classifier: License :: OSI Approved :: MIT License
Classifier: Topic :: Scientific/Engineering
Classifier: Programming Language :: Python
Classifier: Programming Language :: Python :: 3.7
Classifier: Programming Language :: Python :: 3.8
Classifier: Programming Language :: Python :: 3.9
Classifier: Programming Language :: Python :: 3.10
Classifier: Programming Language :: Python :: 3.11
Classifier: Programming Language :: Python :: 3.12
Classifier: Programming Language :: Python :: Implementation :: CPython
Classifier: Programming Language :: Python :: Implementation :: PyPy
Requires-Dist: pandas>1.3.0
Requires-Dist: numpy>1.21.0
Project-URL: Documentation, https://datanest.readthedocs.io
Project-URL: Homepage, https://github.com/praneethnamburi/datanest
Project-URL: Issues, https://github.com/praneethnamburi/datanest/issues
